unilang/__init__.py
unilang/auth/__init__.py
unilang/auth/openai.py
unilang/auth/qianfan.py
unilang/chat/__init__.py
unilang/chat/base.py
unilang/chat/message.py
unilang/chat/qianfan/__init__.py
unilang/chat/qianfan/model.py
unilang/chat/qianfan/model_names.py
unilang/chat/response.py
unilang/chat/role.py
unilang/embedding/__init__.py
unilang/embedding/base.py
unilang/embedding/qianfan/__init__.py
unilang/embedding/qianfan/model.py
unilang/embedding/qianfan/model_names.py
unilang/embedding/response.py
unilang-0.1.0.dist-info/METADATA
unilang-0.1.0.dist-info/WHEEL
unilang-0.1.0.dist-info/RECORD
