Metadata-Version: 2.1
Name: unilang
Version: 0.1.0
Summary: 
Author: isaac-fei
Author-email: isaac.omega.fei@gmail.com
Requires-Python: >=3.11,<4.0
Classifier: Programming Language :: Python :: 3
Classifier: Programming Language :: Python :: 3.11
Requires-Dist: loguru (>=0.7.2,<0.8.0)
Requires-Dist: openai (>=1.3.3,<2.0.0)
Requires-Dist: pydantic (>=2.5.1,<3.0.0)
Requires-Dist: python-dotenv (>=1.0.0,<2.0.0)
Requires-Dist: qianfan (>=0.1.4,<0.2.0)
